kdbq_kernel/__init__.py
kdbq_kernel/__main__.py
kdbq_kernel/images.py
kdbq_kernel/install.py
kdbq_kernel/kernel.py
kdbq_kernel-0.1.dist-info/WHEEL
kdbq_kernel-0.1.dist-info/METADATA
kdbq_kernel-0.1.dist-info/RECORD
