Metadata-Version: 1.2
Name: kdbq_kernel
Version: 0.1
Summary: A Kdb/Q kernel for Jupyter
Home-page: https://github.com/newtux/KdbQ_kernel
License: UNKNOWN
Author: GM
Author-email: newtux@gmail.com
Classifier: Framework :: IPython
Classifier: License :: OSI Approved :: BSD License
Classifier: Topic :: System :: Shells
Requires-Dist: pexpect (>=4.0)
